protool/__init__.py
protool/command_line.py
protool-3.0.0.dist-info/LICENSE
protool-3.0.0.dist-info/METADATA
protool-3.0.0.dist-info/WHEEL
protool-3.0.0.dist-info/entry_points.txt
protool-3.0.0.dist-info/RECORD
