Metadata-Version: 2.1
Name: protool
Version: 3.0.0
Summary: A tool for dealing with provisioning profiles
Home-page: https://github.com/Microsoft/protool
License: MIT
Keywords: provisioning,profiles,apple,ios,xcode,mobileprovision
Author: Dale Myers
Author-email: dalemy@microsoft.com
Requires-Python: >=3.11,<4.0
Classifier: Development Status :: 3 - Alpha
Classifier: Environment :: Console
Classifier: Environment :: MacOS X
Classifier: Intended Audience :: Developers
Classifier: License :: OSI Approved :: MIT License
Classifier: Programming Language :: Python :: 3
Classifier: Programming Language :: Python :: 3.11
Classifier: Programming Language :: Python :: 3.12
Classifier: Programming Language :: Python :: 3.13
Classifier: Programming Language :: Python :: 3.10
Classifier: Programming Language :: Python :: 3.8
Classifier: Programming Language :: Python :: 3.9
Classifier: Topic :: Software Development
Classifier: Topic :: Utilities
Requires-Dist: pyOpenSSL (>=25.1.0,<26.0.0)
Project-URL: Repository, https://github.com/Microsoft/protool
